{
  "sections": {
    "banner": {
      "type": "main-collection-banner",
      "settings": {
      }
    },
    "product-grid": {
      "type": "main-collection-product-grid",
      "settings": {
        "enable_quick_add": true,
        "enable_filtering": true,
        "filter_type": "horizontal",
        "enable_sorting": true,
        "child_collection": true
      }
    },
    "16540387627dd6a3af": {
      "type": "collection-preview",
      "settings": {
        "collection_name": "Concrete Jungle",
        "collection_url": "",
        "product_list": [
          "baldwin-long-short-cream",
          "century-camp-button-up-green-polkadot",
          "century-camp-button-up-peach",
          "inner-city-cinema-t-shirt-blonde",
          "compton-short-black",
          "concrete-jungle-t-shirt-black",
          "century-camp-button-up-cream-polkadot",
          "fairfax-twill-pant-black"
        ],
        "enable_quick_add": true
      }
    },
    "165403876742214c90": {
      "type": "collection-preview",
      "settings": {
        "collection_name": "Inner City",
        "collection_url": "",
        "product_list": [
          "jazz-checkered-short-melon",
          "jazz-checkered-short-black",
          "inner-city-love-t-shirt-black-1",
          "inner-city-love-cap-sage",
          "1988-icon-denim-pant-black",
          "1988-icon-denim-pant-indigo",
          "luther-cargo-pant-clay",
          "inner-city-love-t-shirt-terra-cotta"
        ],
        "enable_quick_add": true
      }
    }
  },
  "order": [
    "banner",
    "product-grid",
    "16540387627dd6a3af",
    "165403876742214c90"
  ]
}
